seagulls/space_shooter/__init__.py
seagulls/space_shooter/_active_ship_client.py
seagulls/space_shooter/_asteroid_field.py
seagulls/space_shooter/_asteroid_missed_rule.py
seagulls/space_shooter/_blue_ship.py
seagulls/space_shooter/_check_game_rules_interface.py
seagulls/space_shooter/_cli_command.py
seagulls/space_shooter/_cli_entry_point.py
seagulls/space_shooter/_cli_plugin.py
seagulls/space_shooter/_di_container.py
seagulls/space_shooter/_empty_ship.py
seagulls/space_shooter/_game_over_overlay.py
seagulls/space_shooter/_game_over_scene.py
seagulls/space_shooter/_laser.py
seagulls/space_shooter/_orange_ship.py
seagulls/space_shooter/_replay_shooter_button.py
seagulls/space_shooter/_score_overlay.py
seagulls/space_shooter/_score_tracker.py
seagulls/space_shooter/_selectable_ship_menu.py
seagulls/space_shooter/_ship.py
seagulls/space_shooter/_ship_button.py
seagulls/space_shooter/_ship_catalog.py
seagulls/space_shooter/_ship_destroyed_rule.py
seagulls/space_shooter/_ship_interfaces.py
seagulls/space_shooter/_shooter_scene.py
seagulls/space_shooter/_shooter_scene_client.py
seagulls/space_shooter/_space_collisions.py
seagulls/space_shooter/_space_rock.py
seagulls/space_shooter/_stars_background.py
seagulls_space_shooter_demo-0.1.0rc1.dist-info/entry_points.txt
seagulls_space_shooter_demo-0.1.0rc1.dist-info/WHEEL
seagulls_space_shooter_demo-0.1.0rc1.dist-info/METADATA
seagulls_space_shooter_demo-0.1.0rc1.dist-info/RECORD
